Metadata-Version: 1.1
Name: myawis
Version: 0.2.3
Summary: A simple AWIS python wrapper
Home-page: https://github.com/ashim888/awis
Author: Ashim Lamichhane
Author-email: punchedrock@gmail.com
License: UNKNOWN
Keywords: python awis api call
Platform: UNKNOWN
Classifier: Development Status :: 2 - Pre-Alpha
Classifier: Intended Audience :: Developers
Classifier: Topic :: Software Development :: Libraries :: Python Modules
Classifier: License :: Public Domain
Classifier: Programming Language :: Python :: 2.6
Classifier: Programming Language :: Python :: 2.7
